catboys/__init__.py
catboys/catboys.py
catboys/dict.py
catboys/errors.py
catboys/http.py
catboys.py-1.0.0.dist-info/LICENSE
catboys.py-1.0.0.dist-info/METADATA
catboys.py-1.0.0.dist-info/WHEEL
catboys.py-1.0.0.dist-info/top_level.txt
catboys.py-1.0.0.dist-info/RECORD
