Metadata-Version: 2.1
Name: catboys.py
Version: 1.0.0
Summary: A Python module that uses the Catboys API
Home-page: https://github.com/Catboys-Dev/catboys.py
Author: Kristian Kramer
Author-email: kristian@catboys.com
License: GNU v3
Platform: UNKNOWN
Requires-Dist: requests
